{
  "forms": [
    {
      "id": "startup-discovery",
      "title": "Startup Discovery",
      "description": "A structured discovery interview to understand a startup idea, its problem space, market, and team readiness.",
      "icon": "🚀",
      "color": "#6366f1",
      "version": "1.0",
      "category": "Business",
      "tags": ["startup", "discovery", "interview"],
      "createdAt": "2026-01-01T00:00:00.000Z",
      "updatedAt": "2026-01-01T00:00:00.000Z",
      "sections": [
        {
          "id": "sec-problem",
          "title": "Problem",
          "description": "Understand the core problem the founder is trying to solve.",
          "summaryTemplate": "The founder describes the problem as: {{answers}}. This section should be evaluated for clarity, evidence of pain, and urgency.",
          "aiPrompt": "Analyze whether the described problem is specific, painful, and validated by real evidence rather than assumption.",
          "questions": [
            {
              "id": "q1",
              "type": "textarea",
              "title": "What problem are you solving?",
              "description": "Describe the core problem in your own words.",
              "placeholder": "e.g. Small businesses struggle to manage inventory across multiple sales channels...",
              "required": true,
              "hint": "Be as specific as possible. Avoid vague statements.",
              "weight": 3,
              "tags": ["problem", "core"],
              "defaultValue": "",
              "questionPrompt": "Evaluate the clarity and specificity of this problem statement.",
              "aiEnabled": true
            },
            {
              "id": "q2",
              "type": "text",
              "title": "Who experiences this problem most acutely?",
              "description": "Name the primary persona or segment.",
              "placeholder": "e.g. Solo restaurant owners with 1-3 locations",
              "required": true,
              "hint": "One sentence is enough.",
              "weight": 2,
              "tags": ["problem", "persona"],
              "defaultValue": "",
              "questionPrompt": "",
              "aiEnabled": false
            },
            {
              "id": "q3",
              "type": "likert",
              "title": "How confident are you that this problem is validated (not assumed)?",
              "description": "Rate your confidence based on real customer conversations, not intuition.",
              "placeholder": "",
              "required": true,
              "hint": "1 = pure assumption, 5 = validated with strong evidence",
              "weight": 3,
              "tags": ["problem", "validation"],
              "defaultValue": "",
              "questionPrompt": "",
              "aiEnabled": false
            }
          ]
        },
        {
          "id": "sec-market",
          "title": "Market",
          "description": "Explore the size, competition, and positioning of the target market.",
          "summaryTemplate": "Market analysis based on founder input: {{answers}}. Assess realism of market sizing and competitive awareness.",
          "aiPrompt": "Assess whether the market description shows awareness of competitors and realistic sizing.",
          "questions": [
            {
              "id": "q4",
              "type": "textarea",
              "title": "Who are your main competitors or alternatives?",
              "description": "Include direct competitors and indirect alternatives (e.g. spreadsheets, manual processes).",
              "placeholder": "e.g. Competitor A, Competitor B, or manual Excel tracking...",
              "required": true,
              "hint": "List at least two alternatives.",
              "weight": 2,
              "tags": ["market", "competition"],
              "defaultValue": "",
              "questionPrompt": "Check if the founder distinguishes direct vs indirect competitors.",
              "aiEnabled": true
            },
            {
              "id": "q5",
              "type": "likert",
              "title": "How well do you understand your target market size?",
              "description": "Rate your confidence in your TAM/SAM/SOM estimates.",
              "placeholder": "",
              "required": true,
              "hint": "1 = no idea, 5 = data-backed estimate",
              "weight": 2,
              "tags": ["market", "sizing"],
              "defaultValue": "",
              "questionPrompt": "",
              "aiEnabled": false
            }
          ]
        },
        {
          "id": "sec-team",
          "title": "Team",
          "description": "Assess the founding team's readiness and relevant experience.",
          "summaryTemplate": "Team readiness summary: {{answers}}. Evaluate domain expertise and execution capacity.",
          "aiPrompt": "Assess whether the team has relevant domain expertise and execution capability for this specific problem.",
          "questions": [
            {
              "id": "q6",
              "type": "text",
              "title": "What relevant experience does your team have?",
              "description": "Domain expertise, past startups, technical skills, etc.",
              "placeholder": "e.g. 5 years in logistics, previously built a SaaS product...",
              "required": false,
              "hint": "",
              "weight": 2,
              "tags": ["team", "experience"],
              "defaultValue": "",
              "questionPrompt": "",
              "aiEnabled": false
            },
            {
              "id": "q7",
              "type": "likert",
              "title": "How committed is the team to working on this full-time?",
              "description": "",
              "placeholder": "",
              "required": true,
              "hint": "1 = side project, 5 = fully committed full-time",
              "weight": 3,
              "tags": ["team", "commitment"],
              "defaultValue": "",
              "questionPrompt": "",
              "aiEnabled": false
            }
          ]
        }
      ]
    }
  ]
}
